CHANGES.txt
LICENSE.txt
README.txt
bootstrap.py
buildout.cfg
setup.py
doc/Example-1.ssd
doc/Example-2.ssd
doc/ExampleInclude.ssd
src/tcm2sql/Constraint.py
src/tcm2sql/Relation.py
src/tcm2sql/Render.py
src/tcm2sql/RenderDB.py
src/tcm2sql/RenderPostgres.py
src/tcm2sql/SSDReader.py
src/tcm2sql/Table.py
src/tcm2sql/__init__.py
src/tcm2sql/helpers.py
src/tcm2sql/tcm2sql.py
src/tcm2sql/tcmfile.py
src/tcm2sql/test.py
src/tcm2sql.egg-info/PKG-INFO
src/tcm2sql.egg-info/SOURCES.txt
src/tcm2sql.egg-info/dependency_links.txt
src/tcm2sql.egg-info/entry_points.txt
src/tcm2sql.egg-info/not-zip-safe
src/tcm2sql.egg-info/requires.txt
src/tcm2sql.egg-info/top_level.txt
src/tcm2sql/tests/__init__.py
src/tcm2sql/tests/pet.ssd
src/tcm2sql/tests/test.ssd
src/tcm2sql/tests/test_helpers.py
src/tcm2sql/tests/test_ssdreader.py
src/tcm2sql/tests/test_tcmfile.py