Metadata-Version: 1.0
Name: tcm2sql
Version: 1.0.0
Summary: Tool for generating SQL commands from a tcm static structure diagram (SSD)
Home-page: http://code.gocept.com
Author: Christian Zagrodnick
Author-email: mail@gocept.com
License: GPL 2
Keywords: sql tcm
Platform: UNKNOWN
Classifier: Development Status :: 4 - Beta
Classifier: Programming Language :: Python
